treeminer/__init__.py
treeminer/miners.py
treeminer/repo.py
treeminer-0.1.0.dist-info/METADATA
treeminer-0.1.0.dist-info/WHEEL
treeminer-0.1.0.dist-info/licenses/LICENSE
treeminer-0.1.0.dist-info/RECORD
